bedger/__init__.py
bedger/edge/__init__.py
bedger/edge/client.py
bedger/edge/config.py
bedger/edge/entities/__init__.py
bedger/edge/entities/device.py
bedger/edge/entities/device_event.py
bedger/edge/entities/device_twin.py
bedger/edge/entities/enums.py
bedger/edge/entities/measurement.py
bedger/edge/entities/severity.py
bedger/edge/errors.py
bedger-0.0.15.dist-info/LICENSE
bedger-0.0.15.dist-info/METADATA
bedger-0.0.15.dist-info/WHEEL
bedger-0.0.15.dist-info/RECORD
